padme_conductor/Query.py
padme_conductor/Separation.py
padme_conductor/TrainLogger.py
padme_conductor/_TrainTagFormatter.py
padme_conductor/__init__.py
padme_conductor/constants.py
padme_conductor/padme_conductor.py
padme_conductor/Plugins/DatabasePlugin.py
padme_conductor/Plugins/FHIR.py
padme_conductor/Plugins/MinIO.py
padme_conductor/Plugins/SQL.py
padme_conductor/Plugins/__init__.py
padme_conductor-0.1.9.dist-info/LICENSE
padme_conductor-0.1.9.dist-info/METADATA
padme_conductor-0.1.9.dist-info/WHEEL
padme_conductor-0.1.9.dist-info/top_level.txt
padme_conductor-0.1.9.dist-info/RECORD
