Metadata-Version: 2.1
Name: padme-conductor
Version: 0.1.9
Summary: A library which supports the creation of so-called Trains for the Personal Health Train infrastructure.
Home-page: https://github.com/sawelt/padme-conductor
Author: Martin Goerz, Sascha Welten
Author-email: welten@dbis.rwth-aachen.de
License: UNKNOWN
Keywords: Personal Health Train,PADME
Platform: UNKNOWN
Classifier: Intended Audience :: Science/Research
License-File: LICENSE
Requires-Dist: fhirpy (~=1.2.1)
Requires-Dist: psycopg2
